{
  "$schema": "https://mintlify.com/docs.json",
  "name": "Rust Ironclad",
  "theme": "aspen",
  "colors": {
    "primary": "#CE422B",
    "light": "#E86B50",
    "dark": "#9C2E1F"
  },
  "navbar": {
    "primary": {
      "type": "github",
      "href": "https://github.com/Vicente-Alejandro/Rust-Ironclad"
    }
  },
  "footer": {
    "socials": {
      "github": "https://github.com/Vicente-Alejandro/Rust-Ironclad"
    }
  },
  "navigation": {
    "tabs": [
      {
        "tab": "Documentation",
        "groups": [
          {
            "group": "Getting Started",
            "pages": [
              "introduction",
              "installation",
              "quickstart",
              "project-structure"
            ]
          },
          {
            "group": "Architecture",
            "pages": [
              "architecture/overview",
              "architecture/domain-driven-design",
              "architecture/layers",
              "architecture/dependency-injection"
            ]
          },
          {
            "group": "Core Concepts",
            "pages": [
              "core-concepts/routing",
              "core-concepts/controllers",
              "core-concepts/services",
              "core-concepts/entities-value-objects",
              "core-concepts/repositories",
              "core-concepts/dtos"
            ]
          },
          {
            "group": "Database",
            "pages": [
              "database/configuration",
              "database/migrations",
              "database/postgres",
              "database/mongodb"
            ]
          },
          {
            "group": "Security",
            "pages": [
              "security/authentication",
              "security/authorization",
              "security/jwt",
              "security/validation"
            ]
          },
          {
            "group": "Advanced",
            "pages": [
              "advanced/middleware",
              "advanced/error-handling",
              "advanced/maintenance-mode",
              "advanced/configuration",
              "advanced/logging"
            ]
          }
        ]
      },
      {
        "tab": "CLI Reference",
        "groups": [
          {
            "group": "Commands",
            "pages": [
              "cli/overview",
              "cli/version",
              "cli/database",
              "cli/maintenance",
              "cli/storage"
            ]
          }
        ]
      },
      {
        "tab": "API Reference",
        "groups": [
          {
            "group": "Modules",
            "pages": [
              "api/application",
              "api/domain",
              "api/infrastructure",
              "api/interfaces",
              "api/bootstrap"
            ]
          }
        ]
      }
    ]
  }
}
